implicature_intent/__init__.py
implicature_intent/consts.py
implicature_intent/engine.py
implicature_intent/llm.py
implicature_intent-0.1.1.dist-info/licenses/LICENSE
implicature_intent-0.1.1.dist-info/METADATA
implicature_intent-0.1.1.dist-info/WHEEL
implicature_intent-0.1.1.dist-info/top_level.txt
implicature_intent-0.1.1.dist-info/RECORD
