Metadata-Version: 2.4
Name: implicature-intent
Version: 0.1.1
Summary: Detect implicit intent vs tone in short conversational turns
Author-email: Loom Labs <opensource@loomlabs.com>
License: MIT
Project-URL: Homepage, https://github.com/loomlabs/implicature-intent
Project-URL: Documentation, https://github.com/loomlabs/implicature-intent#readme
Project-URL: Repository, https://github.com/loomlabs/implicature-intent
Project-URL: Issues, https://github.com/loomlabs/implicature-intent/issues
Keywords: nlp,intent,sentiment,conversational,pragmatics,implicature
Classifier: Development Status :: 4 - Beta
Classifier: Intended Audience :: Developers
Classifier: Intended Audience :: Science/Research
Classifier: Topic :: Scientific/Engineering :: Artificial Intelligence
Classifier: Topic :: Text Processing :: Linguistic
Classifier: Programming Language :: Python :: 3
Classifier: Programming Language :: Python :: 3.8
Classifier: Programming Language :: Python :: 3.9
Classifier: Programming Language :: Python :: 3.10
Classifier: Programming Language :: Python :: 3.11
Classifier: Programming Language :: Python :: 3.12
Classifier: License :: OSI Approved :: MIT License
Classifier: Operating System :: OS Independent
Requires-Python: >=3.8
License-File: LICENSE
Provides-Extra: dev
Requires-Dist: pytest>=7.0; extra == "dev"
Requires-Dist: twine; extra == "dev"
Requires-Dist: build; extra == "dev"
Dynamic: license-file
